{"State.64df3692-dd65-49ee-921d-e3d37bad920e": {"id": "64df3692-dd65-49ee-921d-e3d37bad920e", "created_at": "2024-06-30T16:31:56.723812", "updated_at": "2024-06-30T16:31:56.723846", "name": "California", "__class__": "State"}, "State.29d1975c-8811-4bf0-b6d9-2746252460d3": {"id": "29d1975c-8811-4bf0-b6d9-2746252460d3", "created_at": "2024-06-30T16:31:56.724247", "updated_at": "2024-06-30T16:31:56.724272", "name": "Arizona", "__class__": "State"}, "Place.8798237a-ac70-4d0f-9a6c-c4000fac5912": {"id": "8798237a-ac70-4d0f-9a6c-c4000fac5912", "created_at": "2024-06-30T16:31:56.725396", "updated_at": "2024-06-30T16:31:56.725491", "city_id": "0001", "user_id": "0001", "name": "My little house", "number_rooms": 4, "number_bathrooms": 2, "max_guest": 10, "price_by_night": 300, "latitude": 37.773972, "longitude": -122.431297, "__class__": "Place"}}